asyncpusher/__init__.py
asyncpusher/channel.py
asyncpusher/connection.py
asyncpusher/pusher.py
asyncpusher-0.2.5.dist-info/METADATA
asyncpusher-0.2.5.dist-info/WHEEL
asyncpusher-0.2.5.dist-info/licenses/LICENSE
asyncpusher-0.2.5.dist-info/RECORD
