Metadata-Version: 2.4
Name: asyncpusher
Version: 0.2.5
Summary: An asynchronous Pusher client library
Project-URL: Documentation, https://github.com/byildiz/asyncpusher#readme
Project-URL: Issues, https://github.com/byildiz/asyncpusher/issues
Project-URL: Source, https://github.com/byildiz/asyncpusher
Author-email: Burak Yildiz <0byldz@gmail.com>
License-Expression: MIT
License-File: LICENSE
Keywords: aiohttp,asynchronous,pusher,websocket
Classifier: Development Status :: 4 - Beta
Classifier: Framework :: AsyncIO
Classifier: Framework :: aiohttp
Classifier: License :: OSI Approved :: MIT License
Classifier: Programming Language :: Python
Classifier: Programming Language :: Python :: 3.10
Classifier: Programming Language :: Python :: 3.11
Classifier: Programming Language :: Python :: Implementation :: CPython
Classifier: Topic :: Internet
Requires-Python: >=3.10
Requires-Dist: aiohttp>=3.8
